<?xml version="1.0" encoding="utf-8" ?>

<Defs>
  <ThoughtDef ParentName="DeathMemory">
    <defName>PackMateDied</defName>
    <stackLimit>10</stackLimit>
    <durationDays>30</durationDays>
    <stackLimitForSameOtherPawn>1</stackLimitForSameOtherPawn>
    <stages>
      <li>
        <label>My packmate {0} died.</label>
        <description>One of my packmates died...</description>
        <baseMoodEffect>-15</baseMoodEffect>
      </li>
      <li>
        <label>{0} died.</label>
        <description>I still miss my packmate. I wish they didn't die.</description>
        <baseMoodEffect>-10</baseMoodEffect>
      </li>
    </stages>
  </ThoughtDef>

  <ThoughtDef ParentName="DeathMemoryFamily">
    <defName>AvaliKitDied</defName>
    <stages>
      <li>
        <label>My kit {0} died.</label>
        <description>My kit died.</description>
        <baseMoodEffect>-30</baseMoodEffect>
      </li>
    </stages>
  </ThoughtDef>

  <ThoughtDef>
    <defName>MateDied</defName>
    <stages>
      <li>
        <label>Mate {0} died.</label>
        <description>I am alone.</description>
        <baseMoodEffect>-20</baseMoodEffect>
      </li>
    </stages>
  </ThoughtDef>
</Defs>